splitcopy/__init__.py
splitcopy/ftp.py
splitcopy/get.py
splitcopy/paramikoshell.py
splitcopy/progress.py
splitcopy/put.py
splitcopy/shared.py
splitcopy/splitcopy.py
splitcopy/tests/__init__.py
splitcopy/tests/test_ftp.py
splitcopy/tests/test_get.py
splitcopy/tests/test_paramikoshell.py
splitcopy/tests/test_progress.py
splitcopy/tests/test_put.py
splitcopy/tests/test_shared.py
splitcopy/tests/test_splitcopy.py
splitcopy-1.7.1.dist-info/LICENSE
splitcopy-1.7.1.dist-info/METADATA
splitcopy-1.7.1.dist-info/WHEEL
splitcopy-1.7.1.dist-info/entry_points.txt
splitcopy-1.7.1.dist-info/top_level.txt
splitcopy-1.7.1.dist-info/RECORD
