Metadata-Version: 2.1
Name: splitcopy
Version: 1.7.1
Summary: Improves file transfer rates when copying files to/from JUNOS/EVO/*nix hosts
Home-page: https://github.com/Juniper/splitcopy
Author: Chris Jenn
Author-email: jnpr-community-netdev@juniper.net
License: Apache 2.0
Project-URL: Bug Tracker, https://github.com/Juniper/splitcopy/issues
Keywords: ftp,ssh,scp,transfer
Classifier: Development Status :: 5 - Production/Stable
Classifier: License :: OSI Approved :: Apache Software License
Classifier: Environment :: Console
Classifier: Operating System :: OS Independent
Classifier: Programming Language :: Python :: 3
Classifier: Topic :: System :: Networking
Requires-Python: >=3.6
License-File: LICENSE
Requires-Dist: paramiko
Requires-Dist: scp
Requires-Dist: windows-curses ; sys_platform == "win32"
